{"$schema":"https://vega.github.io/schema/vega-lite/v3.json","title":"Where do you go for Elm news and discussion?","data":{"values":"watering-holes,count,year,sort\nBlog Posts,542,2018,\nthe Elm Slack,534,2018,\nthe Elm Subreddit,506,2018,\nTwitter Discussions,398,2018,\n\"Podcasts (Elm Town, JavaScript to Elm, etc.)\",388,2018,\nthe Elm Discourse,293,2018,\nMeetups,206,2018,\nelm-dev Mailing List,159,2018,\ndev.to,47,2018,\nFacebook Groups,18,2018,\nelm-news.com,16,2018,\nthe Elm Slack,495,2017,\nthe Elm Subreddit,471,2017,\nElm Weekly Newsletter,370,2017,\nTwitter Discussions,363,2017,\nelm-discuss Mailing List,194,2017,\n\"Podcasts (Elm Town, JavaScript to Elm, etc.)\",251,2017,\nelm-dev Mailing List,194,2017,\nFacebook Groups,44,2017,\nBlog Posts,11,2017,\nMeetups,6,2017,\nelm-lang.org,5,2017,\nStackOverflow,5,2017,\nPlanet Elm,4,2017,\nThe Elm Documentation,3,2017,\nIRC,3,2017,\nKnowThen,2,2017,\nGoogle,2,2017,\nDailyDrip,2,2017,\nelm-news.com,2,2017,\n","format":{"type":"csv"}},"config":{"view":{"stroke":"transparent"},"axis":{"domainWidth":1}},"mark":"bar","encoding":{"row":{"field":"watering-holes","type":"nominal","sort":{"field":"count","order":"descending","op":"average"},"header":{"labelAngle":0}},"x":{"aggregate":"sum","field":"count","type":"quantitative","axis":{"title":"Number of Respondents","grid":false}},"y":{"field":"year","type":"nominal","axis":{"title":""}},"color":{"field":"year","type":"ordinal","legend":null}}}
